CHANGES.txt
LICENSE.txt
MANIFEST.in
README.txt
setup.py
js/__init__.py
js.bootstrap_colorpicker.egg-info/PKG-INFO
js.bootstrap_colorpicker.egg-info/SOURCES.txt
js.bootstrap_colorpicker.egg-info/dependency_links.txt
js.bootstrap_colorpicker.egg-info/entry_points.txt
js.bootstrap_colorpicker.egg-info/namespace_packages.txt
js.bootstrap_colorpicker.egg-info/not-zip-safe
js.bootstrap_colorpicker.egg-info/requires.txt
js.bootstrap_colorpicker.egg-info/top_level.txt
js/bootstrap_colorpicker/__init__.py
js/bootstrap_colorpicker/test_bootstrap-colorpicker.txt
js/bootstrap_colorpicker/resources/.DS_Store
js/bootstrap_colorpicker/resources/css/colorpicker.css
js/bootstrap_colorpicker/resources/css/colorpicker.min.css
js/bootstrap_colorpicker/resources/img/alpha.png
js/bootstrap_colorpicker/resources/img/hue.png
js/bootstrap_colorpicker/resources/img/saturation.png
js/bootstrap_colorpicker/resources/js/bootstrap-colorpicker.js
js/bootstrap_colorpicker/resources/js/bootstrap-colorpicker.min.js
js/bootstrap_colorpicker/resources/less/colorpicker.less