Metadata-Version: 1.0
Name: js.bootstrap-colorpicker
Version: 2012.09.29-1
Summary: Fanstatic packaging of Colorpicker for Bootstrap (bootstrap-colorpicker.js)
Home-page: https://bitbucket.org/s_nikolai/js.bootstrap_colorpicker
Author: Nikolai Sevostjanov
Author-email: nikolai.sevostjanov@gmail.com
License: BSD
Platform: UNKNOWN
